calculadora_MaOtg/__init__.py
calculadora_MaOtg/calcular.py
calculadora_MaOtg-0.0.1.dist-info/METADATA
calculadora_MaOtg-0.0.1.dist-info/WHEEL
calculadora_MaOtg-0.0.1.dist-info/top_level.txt
calculadora_MaOtg-0.0.1.dist-info/RECORD
