Metadata-Version: 2.1
Name: calculadora_MaOtg
Version: 0.0.1
Summary: My short description
Home-page: https://github.com/MaOtg/simple-package-template
Author: Mateus O Mendes
Author-email: ortega.mat@outlook.com
Requires-Python: >=3.8
